visoptslider/__init__.py
visoptslider/visoptslider.py
visoptslider-1.0.0.dist-info/LICENSE
visoptslider-1.0.0.dist-info/METADATA
visoptslider-1.0.0.dist-info/WHEEL
visoptslider-1.0.0.dist-info/top_level.txt
visoptslider-1.0.0.dist-info/RECORD
