Metadata-Version: 2.1
Name: visoptslider
Version: 1.0.0
Summary: Qt-based implementation of VisOpt Slider widget
Home-page: https://github.com/yuki-koyama/visoptslider
Author: Yuki Koyama
Author-email: yuki@koyama.xyz
License: UNKNOWN
Platform: UNKNOWN
Classifier: Development Status :: 3 - Alpha
Classifier: Programming Language :: Python :: 3
Classifier: License :: OSI Approved :: MIT License
Classifier: Operating System :: OS Independent
Requires-Dist: matplotlib
Requires-Dist: numpy
Requires-Dist: PySide2
